{
    "swagger": "2.0",
    "info": {
        "title": "EIR System API",
        "contact": {
            "name": "Asliddin Berdiev",
            "url": "https://github.com/asliddinberdiev"
        },
        "version": "v1"
    },
    "host": "localhost:8080",
    "basePath": "/api/v1",
    "paths": {
        "/users": {
            "get": {
                "description": "Fetch list of users",
                "consumes": [
                    "application/json"
                ],
                "produces": [
                    "application/json"
                ],
                "tags": [
                    "users"
                ],
                "summary": "Get users",
                "responses": {
                    "200": {
                        "description": "OK",
                        "schema": {
                            "$ref": "#/definitions/response.Response"
                        }
                    },
                    "500": {
                        "description": "Internal Server Error",
                        "schema": {
                            "$ref": "#/definitions/response.Response"
                        }
                    }
                }
            }
        }
    },
    "definitions": {
        "response.Response": {
            "type": "object",
            "properties": {
                "code": {
                    "type": "integer"
                },
                "data": {},
                "error": {},
                "message": {
                    "type": "string"
                },
                "request_id": {
                    "type": "string"
                },
                "success": {
                    "type": "boolean"
                }
            }
        }
    }
}